.gitignore
LICENSE
README.md
precommit.sh
setup.cfg
setup.py
tox.ini
.github/dependabot.yml
.github/workflows/ci.yml
docs/contributing.md
src/nanoemoji/__init__.py
src/nanoemoji/_version.py
src/nanoemoji/codepoints.py
src/nanoemoji/color_glyph.py
src/nanoemoji/colors.py
src/nanoemoji/config.py
src/nanoemoji/disjoint_set.py
src/nanoemoji/features.py
src/nanoemoji/glyph.py
src/nanoemoji/nanoemoji.py
src/nanoemoji/paint.py
src/nanoemoji/svg.py
src/nanoemoji/svg_path.py
src/nanoemoji/util.py
src/nanoemoji/write_codepoints.py
src/nanoemoji/write_diffreport.py
src/nanoemoji/write_fea.py
src/nanoemoji/write_font.py
src/nanoemoji/write_font2png.py
src/nanoemoji/write_glyphgraph.py
src/nanoemoji/write_pngdiff.py
src/nanoemoji/write_variable_font.py
src/nanoemoji/data/__init__.py
src/nanoemoji/data/_default.toml
src/nanoemoji_yisi.egg-info/PKG-INFO
src/nanoemoji_yisi.egg-info/SOURCES.txt
src/nanoemoji_yisi.egg-info/dependency_links.txt
src/nanoemoji_yisi.egg-info/entry_points.txt
src/nanoemoji_yisi.egg-info/requires.txt
src/nanoemoji_yisi.egg-info/top_level.txt
tests/clocks_colr_1.ttx
tests/clocks_colr_1_noreuse.ttx
tests/clocks_glyf.ttx
tests/clocks_picosvg.ttx
tests/clocks_rects_picosvg.ttx
tests/clocks_rects_untouchedsvg.ttx
tests/codepoints_test.py
tests/color_glyph_test.py
tests/colors_test.py
tests/colr_to_svg.py
tests/colr_to_svg_template.svg
tests/config_test.py
tests/conftest.py
tests/disjont_set_test.py
tests/emoji_u25fd.svg
tests/empty.svg
tests/features_test.py
tests/gradient_non_square_viewbox.svg
tests/gradient_opacity.svg
tests/involutory_matrix.svg
tests/involutory_matrix_picosvg.ttx
tests/linear_gradient_rect.svg
tests/linear_gradient_rect_colr_1.ttx
tests/linear_gradient_rect_from_colr_1.svg
tests/linear_gradient_transform.svg
tests/linear_gradient_transform_2.svg
tests/linear_gradient_transform_3.svg
tests/nanoemoji_test.py
tests/one-o-clock.svg
tests/one_rect.svg
tests/one_rect_glyf.ttx
tests/one_rect_transformed.ttx
tests/outside_viewbox_clipped_colr_1.ttx
tests/outside_viewbox_not_clipped_colr_1.ttx
tests/radial_gradient_rect.svg
tests/radial_gradient_rect_colr_1.ttx
tests/radial_gradient_rect_from_colr_1.svg
tests/radial_gradient_square.svg
tests/radial_gradient_transform.svg
