Metadata-Version: 2.1
Name: nanoemoji-yisi
Version: 0.9.2
Summary: Compiler for color fonts
Home-page: UNKNOWN
Author: Rod S
Author-email: rsheeter@google.com
License: UNKNOWN
Platform: UNKNOWN
Requires-Python: >=3.7
Provides-Extra: test
Provides-Extra: lint
Provides-Extra: dev
License-File: LICENSE
